__init__.py
firefly_exchange_client/__init__.py
firefly_exchange_client/api_service.py
firefly_exchange_client/client.py
firefly_exchange_client/constants.py
firefly_exchange_client/contract_abis.py
firefly_exchange_client/contracts.py
firefly_exchange_client/enumerations.py
firefly_exchange_client/interfaces.py
firefly_exchange_client/onboarding_signer.py
firefly_exchange_client/order_signer.py
firefly_exchange_client/signer.py
firefly_exchange_client/socket_manager.py
firefly_exchange_client/sockets.py
firefly_exchange_client/utilities.py
firefly_exchange_client/websocket_client.py
firefly_exchange_client-0.10.13.dist-info/LICENSE
firefly_exchange_client-0.10.13.dist-info/METADATA
firefly_exchange_client-0.10.13.dist-info/WHEEL
firefly_exchange_client-0.10.13.dist-info/top_level.txt
firefly_exchange_client-0.10.13.dist-info/RECORD
