Metadata-Version: 2.1
Name: firefly_exchange_client
Version: 0.10.13
Summary: Library to interact with firefly exchange protocol including its off-chain api-gateway and on-chain contracts
Project-URL: Homepage, https://github.com/fireflyprotocol/firefly_exchange_client
Project-URL: Bug Reports, https://github.com/fireflyprotocol/firefly_exchange_client/issues
Project-URL: Source, https://github.com/fireflyprotocol/firefly_exchange_client/
Keywords: firefly,exchange,decentralized,perpetuals,blockchain
Requires-Python: >=3.8
License-File: LICENSE
Requires-Dist: web3 ~=6.8.0
Requires-Dist: requests ~=2.28.1
Requires-Dist: python-socketio ~=5.7.2
Requires-Dist: websocket-client ~=1.5.1
